{
  "분위기": 9,
  "음악": 2,
  "데이트": 1,
  "힐링": 1,
  "감성": 1,
  "라떼": 77,
  "말차": 26,
  "에스프레소": 15,
  "바닐라": 7,
  "아메리카노": 5,
  "드립커피": 2,
  "산미": 1,
  "원두": 1,
  "사장": 22,
  "주문": 9,
  "정성": 5,
  "직원": 3,
  "응대": 2,
  "바리스타": 2,
  "예약": 2,
  "친절": 2,
  "부담": 6,
  "퀄리티": 3,
  "가격": 1,
  "합리": 1,
  "비교": 1,
  "젤라또": 14,
  "아이스크림": 5,
  "떡": 1,
  "소르베": 1,
  "평일": 1,
  "티라미수": 4,
  "케이크": 1,
  "포장": 1,
  "선물": 1,
  "convenience": {
    "주차": false,
    "발렛파킹": false,
    "무선 인터넷": true,
    "남/녀 화장실 구분": false,
    "단체 이용 가능": false,
    "대기공간": false,
    "간편결제": false,
    "반려동물 동반": true,
    "유아시설": false,
    "유아의자": false,
    "수유실": false,
    "장애인 주차구역": false,
    "휠체어 이용가능": false,
    "장애인 화장실": false,
    "좌식/입식 선택": false,
    "예약": false,
    "포장": true,
    "배달": false,
    "출장": false,
    "방문접수": false,
    "무료 발렛": false,
    "지역화폐 카드형": false,
    "지역화폐 모바일형": false,
    "지역화폐 지류형": false
  }
}