{
  "id": "1049360887",
  "name": "온리고엔코마켓 성수점",
  "category": "카페,디저트",
  "micro_review": [
    "깔끔한 아메리카노의 깊은 맛"
  ],
  "road_address": "서울 성동구 왕십리로 83-21 디타워동 1층 102호",
  "address": "서울 성동구 성수동1가 685-700",
  "lat": "127.0442263",
  "lon": "37.5438293",
  "business_hours": [
    {
      "day": "토",
      "start": "07:00",
      "end": "20:00",
      "breakHours": [],
      "description": null,
      "lastOrderTimes": [
        {
          "__typename": "LastOrderTimes",
          "type": "영업시간",
          "time": "19:30"
        }
      ]
    },
    {
      "day": "일",
      "start": "07:00",
      "end": "20:00",
      "breakHours": [],
      "description": null,
      "lastOrderTimes": [
        {
          "__typename": "LastOrderTimes",
          "type": "영업시간",
          "time": "19:30"
        }
      ]
    },
    {
      "day": "월",
      "start": "07:00",
      "end": "20:00",
      "breakHours": [],
      "description": null,
      "lastOrderTimes": [
        {
          "__typename": "LastOrderTimes",
          "type": "영업시간",
          "time": "19:30"
        }
      ]
    },
    {
      "day": "화",
      "start": "07:00",
      "end": "20:00",
      "breakHours": [],
      "description": null,
      "lastOrderTimes": [
        {
          "__typename": "LastOrderTimes",
          "type": "영업시간",
          "time": "19:30"
        }
      ]
    },
    {
      "day": "수",
      "start": "07:00",
      "end": "20:00",
      "breakHours": [],
      "description": null,
      "lastOrderTimes": [
        {
          "__typename": "LastOrderTimes",
          "type": "영업시간",
          "time": "19:30"
        }
      ]
    },
    {
      "day": "목(12/25)",
      "start": "07:00",
      "end": "20:00",
      "breakHours": [],
      "description": "성탄절",
      "lastOrderTimes": null
    },
    {
      "day": "금",
      "start": "07:00",
      "end": "20:00",
      "breakHours": [],
      "description": null,
      "lastOrderTimes": [
        {
          "__typename": "LastOrderTimes",
          "type": "영업시간",
          "time": "19:30"
        }
      ]
    }
  ],
  "virtual_phone_number": "0507-1398-7681",
  "url": "https://www.instagram.com/onlygo.seongsu",
  "convenience": {
    "주차": true,
    "발렛파킹": false,
    "무선 인터넷": true,
    "남/녀 화장실 구분": true,
    "단체 이용 가능": true,
    "대기공간": false,
    "간편결제": true,
    "반려동물 동반": true,
    "유아시설": false,
    "유아의자": false,
    "수유실": false,
    "장애인 주차구역": false,
    "휠체어 이용가능": false,
    "장애인 화장실": false,
    "좌식/입식 선택": false,
    "예약": true,
    "포장": true,
    "배달": false,
    "출장": false,
    "방문접수": false,
    "무료 발렛": false,
    "지역화폐 카드형": false,
    "지역화폐 모바일형": false,
    "지역화폐 지류형": false
  },
  "description": "저희 온리고엔코마켓 성수점은 편리한 교통 접근성과 함께 감각적인 인테리어가 돋보이는 대형 카페 공간으로, 들어서는 순간 특별한 분위기를 느낄 수 있는 곳입니다.\n\n신선한 커피와 잘 어우러지는 다양한 디저트와 베이커리가 준비되어 있어,\n눈과 입이 함께 즐거운 경험을 선사해드리며,\n\n실내에 들어서는 순간 감각적이고 특별한 분위기를 온전히 느낄 수 있는 공간입니다.\n\n온리고엔코마켓 성수점은 프리미엄 원두와 정성 가득한 디저트를 제공하는 베이커리 전문 카페 맛집으로 여러분을 초대하겠습니다.\n\n항상 최고의 맛과 만족감을 드리는 온리고엔코마켓 성수점이 되겠습니다.\n\n최고의 품질과 서비스를 제공하기 위해 노력하겠습니다.\n\n[ 찾아오시는 길 ]\n\n서울숲역 4번 출구로 나오신 뒤, 뒤쪽으로 돌아서 몇 걸음만 이동하시면 바로 온리고엔코마켓 성수점이 위치해 있습니다.\n\n주차는 서울숲디타워주차장에 주차해주시면 됩니다.\n\n1만원 이상 주문시 주차 2시간 무료 입니다.\n\n-온리고엔코 마켓 성수점-",
  "Information_facilitie": [
    "단체 이용 가능",
    "반려동물 동반",
    "남/녀 화장실 구분",
    "포장",
    "무선 인터넷",
    "예약",
    "화장실 휠체어 이용가능",
    "출입구 휠체어 이용가능",
    "좌석 휠체어 이용가능",
    "장애인 주차구역"
  ],
  "parking_info": {
    "__typename": "InformationBasicParking",
    "isFree": true,
    "normalFeeDescription": null,
    "extraFeeDescription": null
  },
  "payment_info": [
    "간편결제"
  ],
  "menu": [
    {
      "name": "오렌지자몽주스",
      "price": "8000",
      "description": "",
      "images": []
    },
    {
      "name": "수박주스",
      "price": "7500",
      "description": "",
      "images": []
    },
    {
      "name": "키위주스",
      "price": "8000",
      "description": "",
      "images": []
    },
    {
      "name": "딸기바나나주스",
      "price": "7500",
      "description": "",
      "images": []
    },
    {
      "name": "베이컨에그마요 샌드위치",
      "price": "7000",
      "description": "",
      "images": []
    },
    {
      "name": "르뱅쿠키",
      "price": "4500",
      "description": "",
      "images": [
        "https://ldb-phinf.pstatic.net/20241229_247/1735447327692q2wCW_PNG/IMG_5967.png"
      ]
    },
    {
      "name": "레몬 얼그레이 쿠키",
      "price": "4500",
      "description": "",
      "images": [
        "https://ldb-phinf.pstatic.net/20241229_269/1735447317534P4oa5_PNG/IMG_5972.png"
      ]
    },
    {
      "name": "트리플 초코 쿠키",
      "price": "5000",
      "description": "",
      "images": [
        "https://ldb-phinf.pstatic.net/20241229_12/1735447307935GXo5g_PNG/IMG_5970.png"
      ]
    },
    {
      "name": "아메리카노",
      "price": "5500",
      "description": "",
      "images": [
        "https://ldb-phinf.pstatic.net/20240411_286/1712806123347Si2PH_JPEG/%BE%C6%C0%CC%BD%BA%BE%C6%B8%DE%B8%AE%C4%AB%B3%EB.jpg"
      ]
    },
    {
      "name": "라즈베리 크림치즈 쿠키",
      "price": "5500",
      "description": "",
      "images": [
        "https://ldb-phinf.pstatic.net/20241229_267/1735447296013Fc45M_PNG/IMG_5971.png"
      ]
    },
    {
      "name": "라떼",
      "price": "6000",
      "description": "",
      "images": [
        "https://ldb-phinf.pstatic.net/20240411_121/1712806136410OOr2W_JPEG/%C4%AB%C6%E4%B6%F3%B6%BC.jpg"
      ]
    },
    {
      "name": "카푸치노",
      "price": "6000",
      "description": "",
      "images": []
    },
    {
      "name": "히비스커스",
      "price": "6000",
      "description": "",
      "images": [
        "https://ldb-phinf.pstatic.net/20240411_135/1712806185538mz5ow_JPEG/%C8%F7%B9%CC%BD%BA%C4%BF%BD%BA%C6%BC.jpg"
      ]
    },
    {
      "name": "얼그레이",
      "price": "6000",
      "description": "",
      "images": [
        "https://ldb-phinf.pstatic.net/20240411_33/1712806194319bOUeq_JPEG/%BE%F3%B1%D7%B7%B9%C0%CC%C6%BC.jpg"
      ]
    },
    {
      "name": "복숭아아이스티",
      "price": "6000",
      "description": "",
      "images": []
    },
    {
      "name": "카모마일",
      "price": "6000",
      "description": "",
      "images": [
        "https://ldb-phinf.pstatic.net/20240411_258/1712806203456rEdn3_JPEG/%C4%AB%B8%F0%B8%B6%C0%CF%C6%BC.jpg"
      ]
    },
    {
      "name": "헤이즐넛라떼",
      "price": "6500",
      "description": "",
      "images": [
        "https://ldb-phinf.pstatic.net/20240411_205/1712806149673ANf9k_JPEG/%C7%EC%C0%CC%C1%F1%B3%D3%3A%B9%D9%B4%D2%B6%F3_%B6%F3%B6%BC.jpg"
      ]
    },
    {
      "name": "유자레몬티",
      "price": "6500",
      "description": "",
      "images": [
        "https://ldb-phinf.pstatic.net/20240809_100/1723192563426hRCmc_JPEG/IMG_3982.jpeg"
      ]
    },
    {
      "name": "바닐라라떼",
      "price": "6500",
      "description": "",
      "images": [
        "https://ldb-phinf.pstatic.net/20240411_131/1712806143384p9dBM_JPEG/%C7%EC%C0%CC%C1%F1%B3%D3%3A%B9%D9%B4%D2%B6%F3_%B6%F3%B6%BC.jpg"
      ]
    },
    {
      "name": "레몬에이드",
      "price": "6500",
      "description": "",
      "images": [
        "https://ldb-phinf.pstatic.net/20240411_99/1712806219714dbubn_JPEG/%B7%B9%B8%F3%BF%A1%C0%CC%B5%E5.jpg"
      ]
    },
    {
      "name": "청포도에이드",
      "price": "6500",
      "description": "",
      "images": [
        "https://ldb-phinf.pstatic.net/20240411_92/1712806230214iEtwd_JPEG/%C3%BB%C6%F7%B5%B5%BF%A1%C0%CC%B5%E5.jpg"
      ]
    },
    {
      "name": "자몽에이드",
      "price": "6500",
      "description": "",
      "images": [
        "https://ldb-phinf.pstatic.net/20240411_240/1712806224913EmqKP_JPEG/%C0%DA%B8%F9%BF%A1%C0%CC%B5%E5.jpg"
      ]
    },
    {
      "name": "크리스피 치킨 샌드위치",
      "price": "7000",
      "description": "",
      "images": [
        "https://ldb-phinf.pstatic.net/20241229_204/1735447346946irfvo_PNG/IMG_5969.png"
      ]
    },
    {
      "name": "햄치즈 샌드위치",
      "price": "7000",
      "description": "",
      "images": [
        "https://ldb-phinf.pstatic.net/20241229_50/1735447337685iKmRN_PNG/IMG_5968.png"
      ]
    },
    {
      "name": "어니언프렌치프라이",
      "price": "7000",
      "description": "",
      "images": [
        "https://ldb-phinf.pstatic.net/20240411_86/1712806009227goXIV_JPEG/%BE%EE%B4%CF%BE%F0_%C7%C1%B7%BB%C4%A1_%C7%C1%B6%F3%C0%CC.jpg"
      ]
    },
    {
      "name": "시그니처 크림라떼",
      "price": "7000",
      "description": "",
      "images": [
        "https://ldb-phinf.pstatic.net/20240809_114/1723192105852gFlOG_JPEG/IMG_3979.jpeg"
      ]
    },
    {
      "name": "패션후르츠에이드",
      "price": "7000",
      "description": "",
      "images": [
        "https://ldb-phinf.pstatic.net/20240411_168/1712806213701lTRXl_JPEG/%C6%D0%BC%C7%C8%C4%B8%A3%C3%F7%BF%A1%C0%CC%B5%E5.jpg"
      ]
    },
    {
      "name": "자몽블랙티",
      "price": "7000",
      "description": "",
      "images": [
        "https://ldb-phinf.pstatic.net/20240809_280/1723192577596mBvTT_JPEG/IMG_3980.jpeg"
      ]
    },
    {
      "name": "그린티라떼",
      "price": "7000",
      "description": "",
      "images": [
        "https://ldb-phinf.pstatic.net/20240411_174/17128061574012l1MD_JPEG/%B1%D7%B8%B0%C6%BC%B6%F3%B6%BC.jpg"
      ]
    },
    {
      "name": "흑임자라떼",
      "price": "7000",
      "description": "",
      "images": [
        "https://ldb-phinf.pstatic.net/20240809_12/1723192656912Tv7gF_JPEG/IMG_3981.jpeg"
      ]
    },
    {
      "name": "초코라떼",
      "price": "7000",
      "description": "",
      "images": [
        "https://ldb-phinf.pstatic.net/20240411_239/1712806162573I8vrB_JPEG/%C3%CA%C4%DA%B6%F3%B6%BC.jpg"
      ]
    },
    {
      "name": "플레인요거트",
      "price": "7000",
      "description": "",
      "images": [
        "https://ldb-phinf.pstatic.net/20240411_226/1712806172909giP2e_JPEG/%C7%C3%B7%B9%C0%CE%BF%E4%B0%C5%C6%AE.jpg"
      ]
    },
    {
      "name": "플레인 핫도그",
      "price": "7500",
      "description": "",
      "images": [
        "https://ldb-phinf.pstatic.net/20240809_73/1723191882667hhCBP_JPEG/IMG_3494.jpeg"
      ]
    },
    {
      "name": "청양 핫도그",
      "price": "7500",
      "description": "",
      "images": [
        "https://ldb-phinf.pstatic.net/20240809_185/1723191901789eMIWE_JPEG/IMG_3495.jpeg"
      ]
    },
    {
      "name": "로얄밀크티",
      "price": "7500",
      "description": "",
      "images": []
    },
    {
      "name": "블루베리요거트",
      "price": "7500",
      "description": "",
      "images": [
        "https://ldb-phinf.pstatic.net/20240411_138/1712806179661XU0Uc_JPEG/%BA%ED%B7%E7%BA%A3%B8%AE%BF%E4%B0%C5%C6%AE.jpg"
      ]
    },
    {
      "name": "스트로베리요거트",
      "price": "7500",
      "description": "",
      "images": []
    },
    {
      "name": "100%생과일주스",
      "price": "8000",
      "description": "",
      "images": []
    },
    {
      "name": "소불고기 핫도그",
      "price": "8500",
      "description": "",
      "images": [
        "https://ldb-phinf.pstatic.net/20240809_92/1723191953826llWCE_JPEG/IMG_3492.jpeg"
      ]
    },
    {
      "name": "김치라구 핫도그",
      "price": "9000",
      "description": "",
      "images": [
        "https://ldb-phinf.pstatic.net/20240809_234/1723191971545i0U51_JPEG/IMG_3493.jpeg"
      ]
    },
    {
      "name": "윙봉",
      "price": "9000",
      "description": "",
      "images": [
        "https://ldb-phinf.pstatic.net/20240411_200/1712806003280blFYn_JPEG/%C0%AE%BA%C0.jpg"
      ]
    },
    {
      "name": "전라도묵은지볶음밥",
      "price": "14500",
      "description": "",
      "images": [
        "https://ldb-phinf.pstatic.net/20240411_287/1712805981984uvY6S_JPEG/%B1%E8%C4%A1%BA%BA%C0%BD%B9%E4.jpg"
      ]
    },
    {
      "name": "궁중크림떡볶이",
      "price": "17000",
      "description": "",
      "images": [
        "https://ldb-phinf.pstatic.net/20240411_194/17128059628238ob0F_JPEG/%B1%C3%C1%DF%C5%A9%B8%B2%B6%B1%BA%BA%C0%CC.jpg"
      ]
    }
  ],
  "image_url": [
    "https://ldb-phinf.pstatic.net/20240403_99/1712114972065Sefox_PNG/KakaoTalk_Photo_2024-03-28-16-24-53.png",
    "https://ldb-phinf.pstatic.net/20250312_59/17417656822901q2yQ_PNG/%BB%F7%B5%E5%C0%A7%C4%A1_did.png",
    "https://ldb-phinf.pstatic.net/20241229_72/1735444618285nuGhc_PNG/IMG_5998.png",
    "https://ldb-phinf.pstatic.net/20240910_61/1725949339258aAeKC_JPEG/IMG_4164.jpeg"
  ]
}