{
  "id": "1388756141",
  "name": "시즈니",
  "category": "카페,디저트",
  "micro_review": [
    "커피와 함께하는 완벽한 디저트 타임"
  ],
  "road_address": "서울 성동구 서울숲6길 14 거암아트빌라 2층 201호",
  "address": "서울 성동구 성수동1가 668-13",
  "lat": "127.0430066",
  "lon": "37.5475252",
  "business_hours": [
    {
      "day": "금",
      "start": "11:00",
      "end": "22:00",
      "breakHours": [],
      "description": null,
      "lastOrderTimes": null
    },
    {
      "day": "토",
      "start": "11:00",
      "end": "22:00",
      "breakHours": [],
      "description": null,
      "lastOrderTimes": null
    },
    {
      "day": "일",
      "start": "11:00",
      "end": "22:00",
      "breakHours": [],
      "description": null,
      "lastOrderTimes": null
    },
    {
      "day": "월",
      "start": null,
      "end": null,
      "breakHours": null,
      "description": "정기휴무 (매주 월요일)",
      "lastOrderTimes": null
    },
    {
      "day": "화",
      "start": "11:00",
      "end": "22:00",
      "breakHours": [],
      "description": null,
      "lastOrderTimes": null
    },
    {
      "day": "수",
      "start": "11:00",
      "end": "22:00",
      "breakHours": [],
      "description": null,
      "lastOrderTimes": null
    },
    {
      "day": "목",
      "start": "11:00",
      "end": "22:00",
      "breakHours": [],
      "description": null,
      "lastOrderTimes": null
    }
  ],
  "virtual_phone_number": "0507-1340-4979",
  "url": "https://www.instagram.com/cafe_seasony",
  "convenience": {
    "주차": true,
    "발렛파킹": false,
    "무선 인터넷": false,
    "남/녀 화장실 구분": false,
    "단체 이용 가능": false,
    "대기공간": false,
    "간편결제": false,
    "반려동물 동반": true,
    "유아시설": false,
    "유아의자": false,
    "수유실": false,
    "장애인 주차구역": false,
    "휠체어 이용가능": false,
    "장애인 화장실": false,
    "좌식/입식 선택": false,
    "예약": false,
    "포장": false,
    "배달": false,
    "출장": false,
    "방문접수": false,
    "무료 발렛": false,
    "지역화폐 카드형": false,
    "지역화폐 모바일형": false,
    "지역화폐 지류형": false
  },
  "description": "매달 제철에 맞는 최상의 재료로 음료와 디저트를 만듭니다.\n직접 만든 수제청을 비롯해 고메 A등급 마다가스카르산 바닐라빈을 사용한 음료,\n프랑스산 크림치즈와 국내산 생크림을 사용해 밀가루가 전혀 들어가지 않은 바스크치즈케이크\n\nA great way to feel the season, seasony\n\n시즈니의 바스크치즈케이크는 밀가루가 들어가지 않아 크림치즈의 숙성 시간이 필요합니다.\n\n홀케이크는 최소 2일전 예약 부탁드리며 당일 홀케이크 필요시에는 전화부탁드리겠습니다",
  "Information_facilitie": [
    "반려동물 동반"
  ],
  "parking_info": {
    "__typename": "InformationBasicParking",
    "isFree": true,
    "normalFeeDescription": null,
    "extraFeeDescription": null
  },
  "payment_info": [
    "네이버페이"
  ],
  "menu": [
    {
      "name": "생딸기빙수",
      "price": "24000",
      "description": "",
      "images": [
        "https://ldb-phinf.pstatic.net/20251215_9/176578706489310rGJ_JPEG/IMG_8811.jpeg"
      ]
    },
    {
      "name": "생망고빙수",
      "price": "24000",
      "description": "",
      "images": [
        "https://ldb-phinf.pstatic.net/20250309_25/1741507848747vdM4j_JPEG/IMG_6559.jpeg",
        "https://ldb-phinf.pstatic.net/20250307_201/1741331422440nigWV_JPEG/IMG_6513.jpeg"
      ]
    },
    {
      "name": "보늬밤 바스크 치즈케이크",
      "price": "8400",
      "description": "",
      "images": [
        "https://ldb-phinf.pstatic.net/20241114_73/1731580810457kY8uk_JPEG/IMG_9281.jpeg"
      ]
    },
    {
      "name": "말차 바스크 치즈케이크",
      "price": "8000",
      "description": "",
      "images": [
        "https://ldb-phinf.pstatic.net/20251031_63/17618884483447Tr6a_JPEG/IMG_0281.jpeg"
      ]
    },
    {
      "name": "얼그레이 바스크치 즈케이크",
      "price": "8000",
      "description": "",
      "images": [
        "https://ldb-phinf.pstatic.net/20241114_117/1731580520536CASrd_JPEG/IMG_0361.jpeg"
      ]
    },
    {
      "name": "플레인 바스크 치즈케이크",
      "price": "7400",
      "description": "",
      "images": [
        "https://ldb-phinf.pstatic.net/20241212_172/1733981404798VBMTi_JPEG/IMG_1639.jpeg"
      ]
    },
    {
      "name": "블루베리 바스크 치즈케이크",
      "price": "7600",
      "description": "",
      "images": [
        "https://ldb-phinf.pstatic.net/20240121_232/1705837723156RCLEG_JPEG/DSC01725.jpeg"
      ]
    },
    {
      "name": "초코 바스크 치즈케이크",
      "price": "7700",
      "description": "",
      "images": [
        "https://ldb-phinf.pstatic.net/20230302_281/1677757203844mbn5Q_JPEG/%C3%CA%C4%DA.jpg"
      ]
    },
    {
      "name": "단호박 바스크 치즈케이크",
      "price": "7800",
      "description": "",
      "images": [
        "https://ldb-phinf.pstatic.net/20241114_235/1731565399321dSIxt_JPEG/IMG_9245.jpeg"
      ]
    },
    {
      "name": "자몽에이드",
      "price": "6500",
      "description": "",
      "images": [
        "https://ldb-phinf.pstatic.net/20220724_193/1658649092765NSCxb_JPEG/KakaoTalk_20220722_143805244.jpg"
      ]
    },
    {
      "name": "바닐라빈밀크",
      "price": "6000",
      "description": "",
      "images": [
        "https://ldb-phinf.pstatic.net/20220718_257/1658120395047ATbiR_JPEG/_JS_7745.jpg"
      ]
    },
    {
      "name": "애플시나몬티(시즌메뉴)",
      "price": "6000",
      "description": "",
      "images": [
        "https://ldb-phinf.pstatic.net/20250930_216/175921874484089o6k_JPEG/IMG_9186.jpeg"
      ]
    },
    {
      "name": "고구마라떼(시즌메뉴)",
      "price": "6000",
      "description": "",
      "images": [
        "https://ldb-phinf.pstatic.net/20250930_96/1759218729398MksJ4_JPEG/IMG_9188.jpeg"
      ]
    },
    {
      "name": "청귤에이드(시즌메뉴)",
      "price": "6500",
      "description": "",
      "images": [
        "https://ldb-phinf.pstatic.net/20250930_141/1759218779653b06aO_JPEG/IMG_9187.jpeg"
      ]
    },
    {
      "name": "에스프레소",
      "price": "4500",
      "description": "",
      "images": [
        "https://ldb-phinf.pstatic.net/20220718_291/1658120017420QvblS_JPEG/_JS_7594.jpg"
      ]
    },
    {
      "name": "아메리카노",
      "price": "5000",
      "description": "",
      "images": [
        "https://ldb-phinf.pstatic.net/20220718_57/1658119980576dTCrl_JPEG/_JS_8162.jpg"
      ]
    },
    {
      "name": "카페라떼",
      "price": "5500",
      "description": "",
      "images": [
        "https://ldb-phinf.pstatic.net/20220718_75/1658120047420vzXQM_JPEG/_JS_8166.jpg"
      ]
    },
    {
      "name": "모카라떼",
      "price": "6000",
      "description": "",
      "images": [
        "https://ldb-phinf.pstatic.net/20220718_236/16581200783057OiR7_JPEG/_JS_7595.jpg"
      ]
    },
    {
      "name": "바닐라빈라떼",
      "price": "6500",
      "description": "",
      "images": [
        "https://ldb-phinf.pstatic.net/20220724_99/1658649117077mYqWu_JPEG/KakaoTalk_20220722_150712117_01.jpg"
      ]
    },
    {
      "name": "콜드브루라떼",
      "price": "6000",
      "description": "",
      "images": [
        "https://ldb-phinf.pstatic.net/20220724_252/1658650412422C3u3o_JPEG/KakaoTalk_20220722_145131334_02.jpg"
      ]
    },
    {
      "name": "말차라떼",
      "price": "6000",
      "description": "",
      "images": [
        "https://ldb-phinf.pstatic.net/20221223_8/1671785910368KLqKw_JPEG/1216_seasony_0487.jpg"
      ]
    },
    {
      "name": "초코라떼",
      "price": "6000",
      "description": "",
      "images": [
        "https://ldb-phinf.pstatic.net/20220718_251/1658120320183D52FE_JPEG/_JS_7755.jpg"
      ]
    },
    {
      "name": "민초라떼",
      "price": "6000",
      "description": "",
      "images": [
        "https://ldb-phinf.pstatic.net/20221223_57/16717858847948V5mj_JPEG/1216_seasony_0422.jpg"
      ]
    },
    {
      "name": "쑥라떼",
      "price": "6000",
      "description": "",
      "images": [
        "https://ldb-phinf.pstatic.net/20221223_262/1671784949955r2PyX_JPEG/1216_seasony_0139.jpg"
      ]
    },
    {
      "name": "밀크티",
      "price": "6000",
      "description": "",
      "images": [
        "https://ldb-phinf.pstatic.net/20221223_244/16717858986890bG9G_JPEG/1216_seasony_0194.jpg"
      ]
    },
    {
      "name": "레몬에이드",
      "price": "6500",
      "description": "",
      "images": [
        "https://ldb-phinf.pstatic.net/20220718_261/1658120485009tB2mu_JPEG/_JS_7662.jpg"
      ]
    },
    {
      "name": "자몽티",
      "price": "6000",
      "description": "",
      "images": [
        "https://ldb-phinf.pstatic.net/20220718_155/1658120514011UqQb0_JPEG/_JS_7985.jpg"
      ]
    },
    {
      "name": "레몬티",
      "price": "6000",
      "description": "",
      "images": [
        "https://ldb-phinf.pstatic.net/20220718_221/16581205301180KACW_JPEG/_JS_7976.jpg"
      ]
    },
    {
      "name": "유기농 허브티",
      "price": "5500",
      "description": "",
      "images": [
        "https://ldb-phinf.pstatic.net/20220718_266/16581205532278uj2B_JPEG/_JS_7960.jpg"
      ]
    }
  ],
  "image_url": [
    "https://ldb-phinf.pstatic.net/20240116_192/1705394139263devVi_JPEG/IMG_1743.jpeg",
    "https://ldb-phinf.pstatic.net/20251217_236/1765949457242490aS_JPEG/IMG_8810.jpeg",
    "https://ldb-phinf.pstatic.net/20250624_102/1750706659906JEhRr_JPEG/IMG_2936.jpeg",
    "https://ldb-phinf.pstatic.net/20221216_8/1671186627190zrJvD_JPEG/1216_seasony_0921.jpg",
    "https://ldb-phinf.pstatic.net/20230523_66/1684798040018RgjDb_JPEG/3EB35467-489C-41A3-92C9-F6C1B283819E.jpeg",
    "https://ldb-phinf.pstatic.net/20230523_217/1684798039730GTUOa_JPEG/F98F2812-9511-41E9-A1DB-715D786E9C60.jpeg",
    "https://ldb-phinf.pstatic.net/20230523_47/1684798039921Jg61i_JPEG/0A40B338-8703-4D76-8FF6-98F574FCFABF.jpeg",
    "https://ldb-phinf.pstatic.net/20230523_134/1684798040526W2Yvd_JPEG/D33B2028-9F7F-4F26-9C48-C6EAC43B3266.jpeg",
    "https://ldb-phinf.pstatic.net/20230523_122/1684798037485ff1uc_JPEG/314068AB-2635-4837-9EFD-5DD5C1498A89.jpeg"
  ]
}