{
  "id": "1393149392",
  "name": "성수미술관",
  "category": "테마카페",
  "micro_review": null,
  "road_address": "서울 성동구 성수일로8길 39 지층 B02 성수미술관",
  "address": "서울 성동구 성수동2가 289-14",
  "lat": "127.0548021",
  "lon": "37.5457827",
  "business_hours": [
    {
      "day": "토",
      "start": "12:00",
      "end": "22:00",
      "breakHours": [],
      "description": null,
      "lastOrderTimes": null
    },
    {
      "day": "일",
      "start": "12:00",
      "end": "22:00",
      "breakHours": [],
      "description": null,
      "lastOrderTimes": null
    },
    {
      "day": "월",
      "start": "13:00",
      "end": "20:00",
      "breakHours": [],
      "description": null,
      "lastOrderTimes": null
    },
    {
      "day": "화",
      "start": "13:00",
      "end": "20:00",
      "breakHours": [],
      "description": null,
      "lastOrderTimes": null
    },
    {
      "day": "수(12/24)",
      "start": "12:00",
      "end": "22:00",
      "breakHours": [],
      "description": null,
      "lastOrderTimes": null
    },
    {
      "day": "목(12/25)",
      "start": "12:00",
      "end": "22:00",
      "breakHours": [],
      "description": null,
      "lastOrderTimes": null
    },
    {
      "day": "금",
      "start": "13:00",
      "end": "20:00",
      "breakHours": [],
      "description": null,
      "lastOrderTimes": null
    }
  ],
  "virtual_phone_number": "0507-1324-1143",
  "url": "http://seongsumuseum.com",
  "convenience": {
    "주차": false,
    "발렛파킹": false,
    "무선 인터넷": true,
    "남/녀 화장실 구분": true,
    "단체 이용 가능": true,
    "대기공간": false,
    "간편결제": false,
    "반려동물 동반": false,
    "유아시설": false,
    "유아의자": false,
    "수유실": false,
    "장애인 주차구역": false,
    "휠체어 이용가능": false,
    "장애인 화장실": false,
    "좌식/입식 선택": false,
    "예약": true,
    "포장": false,
    "배달": false,
    "출장": false,
    "방문접수": false,
    "무료 발렛": false,
    "지역화폐 카드형": false,
    "지역화폐 모바일형": false,
    "지역화폐 지류형": false
  },
  "description": "대한민국 유일의 미술카페, 성수미술관 입니다.\n마음 껏 그림을 그리고 사진을 찍어보세요.\n국내 유일의 그림카페 성수미술관에선 도안, 아크릴 물감, 붓 등 그림을 그릴 수 있는 모든 도구가 제공됩니다.\n\n매장별 도안, 백드롭 페인팅 등 재고가 각기 다를 수 있으니,\n원하시는 도안이 있을 경우 필히 매장에 확인 연락 바랍니다.\n\n18시 이후 이용 희망하시는 고객께서는 매장에 꼭 전화 후 방문 부탁드립니다. 감사합니다.",
  "Information_facilitie": [
    "예약",
    "남/녀 화장실 구분",
    "무선 인터넷",
    "단체 이용 가능"
  ],
  "parking_info": null,
  "payment_info": null,
  "menu": [
    {
      "name": "1인 입장권",
      "price": "23000",
      "description": "1인 입장권 입니다.",
      "images": [
        "https://ldb-phinf.pstatic.net/20210110_101/1610279839928l2gPL_JPEG/r64igstiKDNlzWkASX1CR08C.JPG.jpg"
      ]
    },
    {
      "name": "베어브릭 페인팅",
      "price": "12900",
      "description": "키링 12,900원\n소형 17,900원\n중형 19,900원",
      "images": [
        "https://ldb-phinf.pstatic.net/20251219_118/1766115166431UdbKf_JPEG/%BA%A3%BE%EE%BA%EA%B8%AF_%BE%C8%B3%BB_240313.jpg"
      ]
    },
    {
      "name": "LP 페인팅",
      "price": "24800",
      "description": "LP 페인팅 24,800원\n일반 시계 추가 5,000원\n턴테이블 시계 추가 7,000원",
      "images": [
        "https://ldb-phinf.pstatic.net/20251219_256/1766115225789kWkXD_PNG/%C0%CC%BF%EB_%BE%C8%B3%BB.png"
      ]
    }
  ],
  "image_url": [
    "https://ldb-phinf.pstatic.net/20221231_291/1672460189181gdjIy_JPEG/%C0%AF%B3%AA.JPG",
    "https://ldb-phinf.pstatic.net/20221231_264/16724602240982tvf9_JPEG/%C8%AF%BF%AC%BB%E7%C1%F8.jpg",
    "https://ldb-phinf.pstatic.net/20221231_215/1672460189170jkMzR_JPEG/%C4%AB%B8%AE%B3%AA.JPG",
    "https://ldb-phinf.pstatic.net/20200207_234/1581050747910MATEK_JPEG/3kSwMLoba49S87X9IFM_QWaV.jpg",
    "https://ldb-phinf.pstatic.net/20190312_60/1552352783182xanjp_JPEG/bNEIvY3cX_5Uh0Cd1gsjuPRF.jpeg.jpg",
    "https://ldb-phinf.pstatic.net/20221231_213/1672460214263AAPuK_JPEG/%C6%AE%B7%AF%BA%ED%B7%AF.JPG",
    "https://ldb-phinf.pstatic.net/20181126_156/15432055929915ubMm_JPEG/GvY02VAAZTDOFfIaKtd2EAfk.jpg",
    "https://ldb-phinf.pstatic.net/20181126_236/1543205593817LKFHa_JPEG/PUUOEn-rWDD5ZsORClK5pnB9.jpg",
    "https://ldb-phinf.pstatic.net/20181126_159/1543205593563KQYtB_JPEG/wugFPtUDjqC3a_b8dYQWiE9C.jpg",
    "https://ldb-phinf.pstatic.net/20181126_163/1543205595237sw4BF_JPEG/-tVeM-xc3OVXwltfBYAvAv75.jpg",
    "https://ldb-phinf.pstatic.net/20181126_160/1543205593673vSEy8_JPEG/jtEXqA0czJl7W-cGDVdn8G-t.jpg",
    "https://ldb-phinf.pstatic.net/20181126_180/1543205591132itqoT_JPEG/0IpXen8XVePzJk6XvS80qbeo.jpg",
    "https://ldb-phinf.pstatic.net/20181023_228/1540277616142re5ku_JPEG/x2sANxwZks_GPvYXwCd_wIkm.jpeg.jpg",
    "https://ldb-phinf.pstatic.net/20181023_83/15402776337117bL5C_JPEG/JPGfE08uXTpnUv6pa_Vlw123.jpeg.jpg",
    "https://ldb-phinf.pstatic.net/20181023_55/1540277841147UsjF6_JPEG/rJdbYTVVtyireAE_0SdGM8gV.jpeg.jpg",
    "https://ldb-phinf.pstatic.net/20181023_9/1540277597108vroVt_JPEG/jlQjPAWeLrSYOfIphSpU2-6z.jpeg.jpg",
    "https://ldb-phinf.pstatic.net/20181023_172/1540277647739Cm0cH_JPEG/Ci89KTCo5fEhR7TmeNoUqeAy.jpeg.jpg",
    "https://ldb-phinf.pstatic.net/20181023_78/1540277674114QO6mV_JPEG/Khr4oCoFmZ30vbG7PyDbv2Bz.jpeg.jpg",
    "https://ldb-phinf.pstatic.net/20181023_207/1540277814898Vfjq7_JPEG/sqnFp0GL7y4jHaJw0Q0SmcTs.jpeg.jpg",
    "https://ldb-phinf.pstatic.net/20181023_262/1540277849793Q2IhB_JPEG/0Pt1RT0j-SEu6tVKEAGIKhrT.jpeg.jpg",
    "https://ldb-phinf.pstatic.net/20181126_178/15432055901062KJF3_JPEG/s6oUms414zEeTBvcDFNW4Je0.jpg",
    "https://ldb-phinf.pstatic.net/20181126_178/1543205590117uGXNP_JPEG/W9HSlOTXSKSHeP63jiSXV-iE.jpg",
    "https://ldb-phinf.pstatic.net/20181126_24/1543205590125jUci5_JPEG/NauI6bLh6c8Fp5PksnmpCzK4.jpg",
    "https://ldb-phinf.pstatic.net/20181126_10/1543205590114F36eG_JPEG/eRGHZOZQzdQ29HLrtuCVcZEl.jpg",
    "https://ldb-phinf.pstatic.net/20181126_72/1543205590112pMhLq_JPEG/VHS4p2nDihgtQB_XyINf-vXl.jpg",
    "https://ldb-phinf.pstatic.net/20181126_45/1543205590112rKFqf_JPEG/V9RZRxxYIIkysDeEbL4Wtftl.jpg",
    "https://ldb-phinf.pstatic.net/20181126_233/15432055905642kf6y_JPEG/3eJTWnH6sBMEPzkEk3L7xxnd.jpg",
    "https://ldb-phinf.pstatic.net/20181126_77/1543205590746ETNS5_JPEG/RtiywMRIuNBeo1Cr9WMJ3w6Z.jpg",
    "https://ldb-phinf.pstatic.net/20181126_183/1543205590579QuXiM_JPEG/5QI4EvW7_UDIDi-Bo_bm7Q0S.jpg",
    "https://ldb-phinf.pstatic.net/20181126_134/1543205592121eRThu_JPEG/heiq9-FzoCmHpAEJqGBXIZcT.jpg",
    "https://ldb-phinf.pstatic.net/20181126_244/1543205590672kmY6L_JPEG/zRt9w_rir5GcskdcASuzX3AP.jpg",
    "https://ldb-phinf.pstatic.net/20181126_2/1543205590509uwlLV_JPEG/Hsj-8c4kZWdalnoMUg6zXUsb.jpg",
    "https://ldb-phinf.pstatic.net/20181126_154/1543205590619An3bn_JPEG/RZa1im8FdxLPdJGGqb3_V3_H.jpg",
    "https://ldb-phinf.pstatic.net/20181126_116/1543205591079P6d6c_JPEG/4jOT-9ndFfMtE9Q5RhQ1jN-q.jpg",
    "https://ldb-phinf.pstatic.net/20181126_203/1543205591115JDLbq_JPEG/IstMGvlFKZoJoczrdY0IGlN1.jpg",
    "https://ldb-phinf.pstatic.net/20181126_66/1543205591152C9iCm_JPEG/-ibyIixGIsbE-hSDy2e7aX4y.jpg",
    "https://ldb-phinf.pstatic.net/20181126_139/1543205591202fKB4l_JPEG/sO9w_1Ns_-RYiAO5q8aezhjM.jpg",
    "https://ldb-phinf.pstatic.net/20181126_216/1543205591186vxJ3m_JPEG/FRMCAc4xpObiyZMcYUL5aIlQ.jpg",
    "https://ldb-phinf.pstatic.net/20181126_143/1543205591971gEqQD_JPEG/CarhFEwSf0ZRyPZi6xrDEQq_.jpg",
    "https://ldb-phinf.pstatic.net/20181126_136/1543205591848YjN1c_JPEG/o2V32aEU_wt0JvNOo8nAN6hf.jpg",
    "https://ldb-phinf.pstatic.net/20181126_214/1543205592019MokkF_JPEG/EMcl4XIZpSAhbaaePaagbNh6.jpg",
    "https://ldb-phinf.pstatic.net/20181126_137/1543205592035XBfEl_JPEG/cLZoyyhM6uCDEFWRilW1sqcJ.jpg",
    "https://ldb-phinf.pstatic.net/20181126_146/1543205592096I6QnE_JPEG/0a0xvLH-aHoKm3zdXEdfKfTH.jpg",
    "https://ldb-phinf.pstatic.net/20181126_226/1543205592860cOzFD_JPEG/7NYiOThKzIhdKM9q8FD_NCGq.jpg",
    "https://ldb-phinf.pstatic.net/20181126_4/1543205593155h7LYQ_JPEG/14fOGkd-_GtDJVzYrVjWJ4EL.jpg",
    "https://ldb-phinf.pstatic.net/20181126_127/1543205592948y4ow5_JPEG/J-r1ecJEeZeZ8ogDuMQ4fmk2.jpg",
    "https://ldb-phinf.pstatic.net/20181126_39/1543205593253LmBnO_JPEG/UC9Sv5RV3kQD8Upn4qvTUhn-.jpg",
    "https://ldb-phinf.pstatic.net/20181126_223/1543205595473v1sd3_JPEG/KhpX0yD-J9JBm0EERyCAz66H.jpg",
    "https://ldb-phinf.pstatic.net/20181126_113/1543205593209LefvY_JPEG/8ve7kt6u7VbPOjDR3u_0P3xj.jpg",
    "https://ldb-phinf.pstatic.net/20181126_203/1543205594433NhurD_JPEG/adEy0vvRBB7RvyY6PPzkZY6I.jpg",
    "https://ldb-phinf.pstatic.net/20181126_253/1543205593928gzc5V_JPEG/EYkyCVKF_iGggg3_-aIW805a.jpg",
    "https://ldb-phinf.pstatic.net/20181126_190/15432055939331bgO7_JPEG/8H4nxSpljntKzNZ4lZLp_ITi.jpg",
    "https://ldb-phinf.pstatic.net/20181126_17/1543205594024ERpeu_JPEG/QBjQqE8Csgnn06E3YIgnVlsh.jpg",
    "https://ldb-phinf.pstatic.net/20181126_171/154320559579786y3s_JPEG/VJny0AHPIwUlhTeSmndOGR-5.jpg",
    "https://ldb-phinf.pstatic.net/20181126_220/1543205593919qohGz_JPEG/2QAEEidKQr08r28QgAHuICJi.jpg",
    "https://ldb-phinf.pstatic.net/20181126_253/1543205594627qkfQD_JPEG/jkWFZRx2xKKJH1NE00j2wCzZ.jpg",
    "https://ldb-phinf.pstatic.net/20181126_174/1543205594459zDBBN_JPEG/n3n3cbAXhSKPBtZoQYH4PFh2.jpg",
    "https://ldb-phinf.pstatic.net/20181126_187/1543205594512EEuLU_JPEG/FLumlzLDCQXeGMLUx3S-bXMf.jpg",
    "https://ldb-phinf.pstatic.net/20181126_58/1543205594665o1YYK_JPEG/_niJOQlYt-9XAwoNLdsiCryX.jpg",
    "https://ldb-phinf.pstatic.net/20181126_27/1543205594926ByPvR_JPEG/vAs605jz5Tj6BXzfAg9CtLop.jpg",
    "https://ldb-phinf.pstatic.net/20181126_142/1543205594831a7rKB_JPEG/Q5ep1caSNHfzHh5Mx5z0OLNR.jpg",
    "https://ldb-phinf.pstatic.net/20181126_257/1543205594956ldz6Q_JPEG/QDLOO_wCu-YeoYXcdpyxU2H4.jpg",
    "https://ldb-phinf.pstatic.net/20181126_23/1543205595024Eaw0p_JPEG/ekIY2nmE09KJZZ9CGxLK3LG5.jpg",
    "https://ldb-phinf.pstatic.net/20181126_104/1543205595331adqEA_JPEG/UjEsTlY5r8RbU2Pzc6L9aGO5.jpg",
    "https://ldb-phinf.pstatic.net/20181126_291/1543205595413ewdX6_JPEG/xi6Xj4hEf6OoRKIVI5Cj0iCW.jpg",
    "https://ldb-phinf.pstatic.net/20181126_224/1543205595537wiOFS_JPEG/mgjum-lcIIuqUENcDuc2d6U4.jpg",
    "https://ldb-phinf.pstatic.net/20181126_205/1543205595422PmKi1_JPEG/o-xItShEfW85VE_MQ2LniQjI.jpg",
    "https://ldb-phinf.pstatic.net/20181126_184/1543205595904HBbBo_JPEG/UWJvCe7inKDnEaaNgT17qmC7.jpg",
    "https://ldb-phinf.pstatic.net/20181126_170/154320559634741lrT_JPEG/0g8miZdLeCfF1aJdlmTXajXo.jpg"
  ]
}