{
  "id": "1461908908",
  "name": "탐앤탐스 성수1호점",
  "category": "카페",
  "micro_review": null,
  "road_address": "서울 성동구 성수이로 51 1층",
  "address": "서울 성동구 성수동2가 325-2",
  "lat": "127.0551423",
  "lon": "37.5400146",
  "business_hours": [
    {
      "day": "금",
      "start": "07:00",
      "end": "02:00",
      "breakHours": [],
      "description": null,
      "lastOrderTimes": [
        {
          "__typename": "LastOrderTimes",
          "type": "영업시간",
          "time": "01:45"
        }
      ]
    },
    {
      "day": "토",
      "start": "09:00",
      "end": "02:00",
      "breakHours": [],
      "description": null,
      "lastOrderTimes": [
        {
          "__typename": "LastOrderTimes",
          "type": "영업시간",
          "time": "01:45"
        }
      ]
    },
    {
      "day": "일",
      "start": "09:00",
      "end": "23:00",
      "breakHours": [],
      "description": null,
      "lastOrderTimes": [
        {
          "__typename": "LastOrderTimes",
          "type": "영업시간",
          "time": "22:45"
        }
      ]
    },
    {
      "day": "월",
      "start": "07:00",
      "end": "02:00",
      "breakHours": [],
      "description": null,
      "lastOrderTimes": [
        {
          "__typename": "LastOrderTimes",
          "type": "영업시간",
          "time": "01:45"
        }
      ]
    },
    {
      "day": "화",
      "start": "07:00",
      "end": "02:00",
      "breakHours": [],
      "description": null,
      "lastOrderTimes": [
        {
          "__typename": "LastOrderTimes",
          "type": "영업시간",
          "time": "01:45"
        }
      ]
    },
    {
      "day": "수",
      "start": "07:00",
      "end": "02:00",
      "breakHours": [],
      "description": null,
      "lastOrderTimes": [
        {
          "__typename": "LastOrderTimes",
          "type": "영업시간",
          "time": "01:45"
        }
      ]
    },
    {
      "day": "목(12/25)",
      "start": "09:00",
      "end": "02:00",
      "breakHours": [],
      "description": "성탄절",
      "lastOrderTimes": null
    }
  ],
  "virtual_phone_number": null,
  "url": null,
  "convenience": {
    "주차": true,
    "발렛파킹": false,
    "무선 인터넷": true,
    "남/녀 화장실 구분": false,
    "단체 이용 가능": false,
    "대기공간": false,
    "간편결제": false,
    "반려동물 동반": false,
    "유아시설": false,
    "유아의자": false,
    "수유실": false,
    "장애인 주차구역": false,
    "휠체어 이용가능": false,
    "장애인 화장실": false,
    "좌식/입식 선택": false,
    "예약": false,
    "포장": true,
    "배달": false,
    "출장": false,
    "방문접수": false,
    "무료 발렛": false,
    "지역화폐 카드형": false,
    "지역화폐 모바일형": false,
    "지역화폐 지류형": false
  },
  "description": "탐앤탐스 성수1호점의 스마트 주문 페이지 입니다.",
  "Information_facilitie": [
    "포장",
    "무선 인터넷"
  ],
  "parking_info": {
    "__typename": "InformationBasicParking",
    "isFree": null,
    "normalFeeDescription": null,
    "extraFeeDescription": null
  },
  "payment_info": [
    "제로페이",
    "네이버페이"
  ],
  "menu": [
    {
      "name": "아메리카노",
      "price": "4600",
      "description": "",
      "images": [
        "https://ldb-phinf.pstatic.net/20200219_287/1582115152972sTj1Q_PNG/R8GuZKRH255EF00r4N-QiGSm.png",
        "https://ldb-phinf.pstatic.net/20200219_60/1582115158095ubuof_PNG/RLHERvrBaUsQ3mpRVBN6MWjZ.png",
        "https://ldb-phinf.pstatic.net/20200219_165/1582115164126ODo3t_PNG/Y7KDUL5MO4CF3aBGdQc0d2NJ.png",
        "https://ldb-phinf.pstatic.net/20200219_30/1582115167829iTwoB_PNG/QlU9H-2_aTPJ6ojJL_vJxzYc.png",
        "https://ldb-phinf.pstatic.net/20200219_8/1582115172349GQpG8_PNG/gYOsZBM6Z_oYVs68r_Q5u3kJ.png"
      ]
    },
    {
      "name": "오리지널 프레즐",
      "price": "5200",
      "description": "탐앤탐스의 대표적인 불로기 , 페퍼로니 프레즐 등 제품(차액 O)",
      "images": [
        "https://ldb-phinf.pstatic.net/20200219_170/1582115223356arfkl_PNG/wjxkb0E4brzZuX_XQWPdu1mG.png",
        "https://ldb-phinf.pstatic.net/20200219_150/1582115227435rfy3n_PNG/aeX1Xmv0dpupVTfpMYhRBKci.png",
        "https://ldb-phinf.pstatic.net/20200219_198/15821152313744lv4y_PNG/A-XgrXkn5rQAtZkVBavEdLab.png",
        "https://ldb-phinf.pstatic.net/20200219_260/1582115237958sAKMG_PNG/6LwwGnM2XZHxU5eugbPkmqXd.png",
        "https://ldb-phinf.pstatic.net/20200219_287/15821152417489Ioin_PNG/EQ846AWG-j-R7XqJuIPW_NtI.png"
      ]
    }
  ],
  "image_url": [
    "https://ldb-phinf.pstatic.net/20200225_136/1582631972557sVS63_JPEG/XxQXMtK2prOyJ3ayfLlZ5_lN.jpg",
    "https://ldb-phinf.pstatic.net/20200225_132/1582631964883x0lBC_JPEG/boN_tHQ2KiFZOa6_oJRwHMHJ.jpg",
    "https://ldb-phinf.pstatic.net/20200225_260/1582631988381DrpQp_JPEG/xui9pmBMR9SE3QqeXCa8u6qJ.jpg",
    "https://ldb-phinf.pstatic.net/20200225_52/1582631993795mWgia_JPEG/wNCbrNCwf118GIb8YT1aetjH.jpg",
    "https://ldb-phinf.pstatic.net/20200225_51/1582632001798ymRGo_JPEG/9nIQoPIE_DuR8YvOr4X4iNQ5.jpg",
    "https://ldb-phinf.pstatic.net/20200225_127/1582632008846JMx1y_JPEG/JVQl6ip1sSKFSmAZLBaZeRD9.jpg",
    "https://ldb-phinf.pstatic.net/20200225_52/1582632016299exUi0_JPEG/3QUj9waJUAkr39XK56fiFoZY.jpg",
    "https://ldb-phinf.pstatic.net/20200708_127/1594171425756wt7iX_PNG/%BE%C6%B8%DE%B8%AE%C4%AB%B3%EB_T_.png"
  ]
}