{
  "id": "1793394506",
  "name": "포레스트 성수 카페",
  "category": "카페,디저트",
  "micro_review": [
    "맛과 분위기 모두 잡은 성수 핫플"
  ],
  "road_address": "서울 성동구 서울숲4길 12-8 1층",
  "address": "서울 성동구 성수동1가 685-259",
  "lat": "127.0420488",
  "lon": "37.5474237",
  "business_hours": [
    {
      "day": "금",
      "start": "11:30",
      "end": "20:00",
      "breakHours": [],
      "description": null,
      "lastOrderTimes": null
    },
    {
      "day": "토",
      "start": "11:30",
      "end": "20:00",
      "breakHours": [],
      "description": null,
      "lastOrderTimes": null
    },
    {
      "day": "일",
      "start": "11:30",
      "end": "20:00",
      "breakHours": [],
      "description": null,
      "lastOrderTimes": null
    },
    {
      "day": "월",
      "start": "11:30",
      "end": "20:00",
      "breakHours": [],
      "description": null,
      "lastOrderTimes": null
    },
    {
      "day": "화",
      "start": "11:30",
      "end": "20:00",
      "breakHours": [],
      "description": null,
      "lastOrderTimes": null
    },
    {
      "day": "수",
      "start": "11:30",
      "end": "20:00",
      "breakHours": [],
      "description": null,
      "lastOrderTimes": null
    },
    {
      "day": "목(12/25)",
      "start": "11:30",
      "end": "20:00",
      "breakHours": [],
      "description": "성탄절",
      "lastOrderTimes": null
    }
  ],
  "virtual_phone_number": null,
  "url": "https://www.instagram.com/forest_seongsu",
  "convenience": {
    "주차": false,
    "발렛파킹": false,
    "무선 인터넷": true,
    "남/녀 화장실 구분": true,
    "단체 이용 가능": false,
    "대기공간": false,
    "간편결제": false,
    "반려동물 동반": false,
    "유아시설": false,
    "유아의자": false,
    "수유실": false,
    "장애인 주차구역": false,
    "휠체어 이용가능": false,
    "장애인 화장실": false,
    "좌식/입식 선택": false,
    "예약": false,
    "포장": true,
    "배달": false,
    "출장": false,
    "방문접수": false,
    "무료 발렛": false,
    "지역화폐 카드형": false,
    "지역화폐 모바일형": false,
    "지역화폐 지류형": false
  },
  "description": "서웊숲 속 휴식의 공간, 포레스트 성수 카페.\n\n포레스트 성수 디저트 카페는 아늑한 휴식과, 편안한 공간의 숲으로 재해석된 공간입니다. 직관적인 나무들이 있는 숲 보다는 누군가의 휴식처와 안식처가 되는 공간의 숲을 지향합니다.\n\n포레스트 성수 카페는 상품의 컨셉과 방향성을 명확하게 통일시키기 위해, 시즌별로 다양한 숲을 소개하는 공간으로 나아가고자 합니다.\n\n나무들의 아늑한 휴식처가 숲이라면, 곰돌이들의 숲은 통나무, 팬더들의 숲은 대나무, 오리들의 숲은 연못, 우리들의 숲은 포레스트 성수 카페 매장이 됩니다.\n\n당신의 숲은 어디인가요?",
  "Information_facilitie": [
    "핸드드립",
    "테이크아웃 할인",
    "무선 인터넷",
    "남/녀 화장실 구분",
    "포장"
  ],
  "parking_info": null,
  "payment_info": [
    "제로페이"
  ],
  "menu": [
    {
      "name": "포레스트 티라미수",
      "price": "9500",
      "description": "고급 마스카포네와 포레스트 블랜딩커피가 어우러져 부드럽고 풍미 가득한 케이크 토끼의 숲",
      "images": [
        "https://ldb-phinf.pstatic.net/20250816_145/1755325350157HP4uE_JPEG/1000020559.jpg"
      ]
    },
    {
      "name": "포레스트 로그",
      "price": "9500",
      "description": "프랑스 발로나 초콜릿으로 초코의 깊은맛과 산뜻한 라즈베리가 어우러진 대표 \"곰돌이의 숲\"",
      "images": [
        "https://ldb-phinf.pstatic.net/20250219_16/17399344098039PywJ_JPEG/1000018160.jpg"
      ]
    },
    {
      "name": "그린 트리",
      "price": "9500",
      "description": "쌉싸름한 녹차향과 달콤한 초콜릿이 만나 부드러운 초코녹차케이크 \"팬더의 숲\"",
      "images": [
        "https://ldb-phinf.pstatic.net/20250219_39/1739934418681zfEgT_JPEG/1000018161.jpg"
      ]
    },
    {
      "name": "치즈 폰드",
      "price": "10500",
      "description": "진한 치즈의 풍미와 바삭한 쿠키가 상큼한 블루베리를 만나 진한 치즈케이크 \"오리들의 숲\"",
      "images": [
        "https://ldb-phinf.pstatic.net/20250219_60/1739934400411utiqw_JPEG/1000018163.jpg"
      ]
    },
    {
      "name": "스몰 트리",
      "price": "10500",
      "description": "벨기에산 화이트 초콜릿의 풍미가 가득 느껴지는 부드러운 포레스트 스몰트리 케이크",
      "images": [
        "https://ldb-phinf.pstatic.net/20250605_273/1749115161178HCqxo_JPEG/1000018663.jpg"
      ]
    },
    {
      "name": "포레스트 로그 미니 홀케이크",
      "price": "29000",
      "description": "프랑스 발로나 초콜릿으로 초코의 깊은맛과 산뜻한 라즈베리가 어우러진 대표 \"곰돌이의 숲\"",
      "images": [
        "https://ldb-phinf.pstatic.net/20251125_18/1764038827468gJkz0_JPEG/%C8%A6%B7%CE%B1%D7_%B4%A9%B3%A2.jpg"
      ]
    },
    {
      "name": "포레스트 트리 미니 홀케이크",
      "price": "29000",
      "description": "생딸기가 가득 들어간 시즌 포레스트 트리 미니 홀케이크",
      "images": [
        "https://ldb-phinf.pstatic.net/20251125_213/1764038873613BVxUB_JPEG/%C8%A6%C6%AE%B8%AE_%B4%A9%B3%A2.jpg"
      ]
    },
    {
      "name": "만다린 오렌지 미니 홀케이크",
      "price": "27500",
      "description": "상큼한 오렌지 생크림과 생과일 오렌지와 만다린(감귤)이 올라간 달콤상큼한 만다린오렌지의 숲",
      "images": [
        "https://ldb-phinf.pstatic.net/20251125_31/17640389253569r67L_JPEG/%C8%A6_%B8%B8%B4%D9%B8%B0_%B4%A9%B3%A2.jpg"
      ]
    },
    {
      "name": "포레스트 티라미수 미니 홀케이크",
      "price": "26000",
      "description": "고급 마스카포네와 포레스트 블랜딩커피가 어우러져 부드럽고 풍미 가득한 케이크 토끼의 숲",
      "images": [
        "https://ldb-phinf.pstatic.net/20251125_226/1764039030399iFnE3_JPEG/%C8%A6%C6%BC%B6%F3%B9%CC%BC%F6_%B4%A9%B3%A2.jpg"
      ]
    },
    {
      "name": "포레스트 베베 만다린오렌지",
      "price": "12000",
      "description": "상큼한 오렌지 생크림과 생과일 오렌지와 만다린(감귤)이 올라간 달콤상큼한 만다린오렌지의 숲",
      "images": [
        "https://ldb-phinf.pstatic.net/20250816_169/1755325167149nvSJu_JPEG/1000020558.jpg"
      ]
    },
    {
      "name": "난나넛 크림라떼 - SIGNATUR",
      "price": "7000",
      "description": "달콤한 생과일 바나나가 우유와 만나 고소한 견과류 크림과 에스프레소가 매력적인 크림라떼",
      "images": [
        "https://ldb-phinf.pstatic.net/20250112_16/1736661830595CRIFH_JPEG/%BD%C3%B1%D7%B4%CF%C3%B3_%B3%AD%B3%AA%B3%D3.jpg"
      ]
    },
    {
      "name": "투리 숲 크림라떼 - SIGNATUR",
      "price": "7000",
      "description": "중독적인 쑥과 녹차가 크림과 우유가 매력적인 시원한 Two리 숲 크림라떼",
      "images": [
        "https://ldb-phinf.pstatic.net/20250112_137/1736661883886XE3vo_JPEG/%BD%C3%B1%D7%B4%CF%C3%B3_%C5%F5%B8%AE%BD%A3.jpg"
      ]
    },
    {
      "name": "그림자 숲 - SIGNATUR",
      "price": "7000",
      "description": "고소한 흑임자의 풍미와 에스프레소가 어우러져 고소달콤한 커피크림라떼 그림자 숲",
      "images": [
        "https://ldb-phinf.pstatic.net/20250112_165/1736661787571l8nEd_JPEG/%BD%C3%B1%D7%B4%CF%C3%B3_%B1%D7%B8%B2%C0%DA_%BD%A3.jpg"
      ]
    },
    {
      "name": "망고 빙수",
      "price": "17800",
      "description": "달콤한 생망고 가득 올린 위에 부드러운 우유폼이 환상의 조화로운 우유 눈꽃 빙수",
      "images": [
        "https://ldb-phinf.pstatic.net/20250219_112/1739934671473tbWGm_JPEG/1000018168.jpg"
      ]
    },
    {
      "name": "멜론 빙수",
      "price": "17800",
      "description": "멜론의 귀족 달콤한 머스크멜론이 듬뿍 올라간 우유 눈꽃 빙수",
      "images": [
        "https://ldb-phinf.pstatic.net/20250219_63/1739934685164ApHMB_JPEG/1000018167.jpg"
      ]
    },
    {
      "name": "스위트 요거트 빙수 - SEASON",
      "price": "11800",
      "description": "상큼하며 스위트한 요거트 우유 얼음 위에 그래놀라와 요거트폼이 어우러진 눈꽃 빙수",
      "images": [
        "https://ldb-phinf.pstatic.net/20250219_290/1739934692509A6a1R_JPEG/1000018170.jpg"
      ]
    },
    {
      "name": "밀크티넛 빙수 - SEASON",
      "price": "10800",
      "description": "밀크티의 풍미가 가득 느껴지는 밀크티 우유 빙수위에 밀크티폼과 견과류가 조화로운 눈꽃 빙수",
      "images": [
        "https://ldb-phinf.pstatic.net/20250219_227/1739934700378QRx0r_JPEG/1000018171.jpg"
      ]
    },
    {
      "name": "아메리카노",
      "price": "5000",
      "description": "다크초콜릿의 중후함, 풍부한 바디감과 견과류의 쌉쌀함이 특징인 포레스트 블랜딩 원두커피",
      "images": [
        "https://ldb-phinf.pstatic.net/20250103_276/17358757175792mUvf_JPEG/%BE%C6%B8%DE%B8%AE%C4%AB%B3%EB.jpg"
      ]
    },
    {
      "name": "리얼 발로나 모카(HOT)",
      "price": "6200",
      "description": "순수 프랑스 발로나 초콜릿만으로만 우유와 에스프레소가 함께 어울리는 리얼 카카오 모카",
      "images": [
        "https://ldb-phinf.pstatic.net/20250112_53/1736662493623VS92j_JPEG/%B8%AE%BE%F3_%B9%DF%B7%CE%B3%AA_%B8%F0%C4%AB_%28HOT%29.jpg"
      ]
    },
    {
      "name": "리얼 발로나 모카(ICED)",
      "price": "6200",
      "description": "순수 프랑스 발로나 초콜릿만으로만 우유와 에스프레소가 함께 어울리는 리얼 카카오 모카",
      "images": [
        "https://ldb-phinf.pstatic.net/20250112_108/1736662518449dIgVJ_JPEG/%B8%AE%BE%F3_%B9%DF%B7%CE%B3%AA_%B8%F0%C4%AB_%28ICED%29.jpg"
      ]
    },
    {
      "name": "로열레몬허니티(HOT)",
      "price": "6000",
      "description": "벌이 꽃에서 직접 추출한 고급진 천연꿀과 상큼한 생과일 레몬즙이 들어간 로열 레몬허니티",
      "images": [
        "https://ldb-phinf.pstatic.net/20250112_267/173666253801452OnT_JPEG/%B7%CE%BF%AD%B7%B9%B8%F3%C7%E3%B4%CF%C6%BC_%28HOT%29.jpg"
      ]
    },
    {
      "name": "로열레몬허니티(ICED)",
      "price": "6000",
      "description": "벌이 꽃에서 직접 추출한 고급진 천연꿀과 상큼한 생과일 레몬즙이 들어간 로열 레몬허니티",
      "images": [
        "https://ldb-phinf.pstatic.net/20250112_52/1736662559599iPp4k_JPEG/%B7%CE%BF%AD%B7%B9%B8%F3%C7%E3%B4%CF%C6%BC_%28ICED%29.jpg"
      ]
    },
    {
      "name": "피치우롱티(HOT)",
      "price": "5000",
      "description": "달달하고 산뜻한 복숭아향이 매력적인 피치 우롱티",
      "images": [
        "https://ldb-phinf.pstatic.net/20250112_244/1736662197469Ds03G_JPEG/%C7%C7%C4%A1%BF%EC%B7%D5%C6%BC_%28HOT%29.jpg"
      ]
    },
    {
      "name": "피치우롱티(ICED)",
      "price": "5000",
      "description": "달달하고 산뜻한 복숭아향이 매력적인 피치 우롱티",
      "images": [
        "https://ldb-phinf.pstatic.net/20250112_242/1736662257470l6nYl_JPEG/%C7%C7%C4%A1%BF%EC%B7%D5%C6%BC_%28ICED%29.jpg"
      ]
    },
    {
      "name": "리얼 발로나 초코(HOT)",
      "price": "5500",
      "description": "순수 프랑스 발로나 초콜릿만으로만 우유와 함께 녹여 리얼 카카오 초코라떼",
      "images": [
        "https://ldb-phinf.pstatic.net/20250112_207/1736662410344HWeCf_JPEG/%B8%AE%BE%F3_%B9%DF%B7%CE%B3%AA_%C3%CA%C4%DA_%28HOT%29.jpg"
      ]
    },
    {
      "name": "리얼발로나 초코(ICED)",
      "price": "5500",
      "description": "순수 프랑스 발로나 초콜릿만으로만 우유와 함께 녹여 리얼 카카오 초코라떼",
      "images": [
        "https://ldb-phinf.pstatic.net/20250112_177/1736662469467xW29E_JPEG/%B8%AE%BE%F3%B9%DF%B7%CE%B3%AA_%C3%CA%C4%DA_%28ICED%29.jpg"
      ]
    },
    {
      "name": "미니치노 (Only HOT)",
      "price": "5000",
      "description": "부드러운 우유와 꿀이 살짝 어우러진 달달한 따뜻한 우유라떼",
      "images": [
        "https://ldb-phinf.pstatic.net/20250112_6/1736662376898oX2lV_JPEG/%B9%CC%B4%CF%C4%A1%B3%EB_%28Only_HOT%29.jpg"
      ]
    },
    {
      "name": "옐로우힙 아이스티",
      "price": "6300",
      "description": "생과일 오렌지를 착즙하여, 포레스트 블랜딩 가을티와 만나 상큼하고 시원한 아이스티",
      "images": [
        "https://ldb-phinf.pstatic.net/20250112_233/1736661941730qLxC5_JPEG/%BD%C3%B1%D7%B4%CF%C3%B3_%BF%BB%B7%CE%BF%EC%C8%FC%BE%C6%C0%CC%BD%BA%C6%BC.jpg"
      ]
    }
  ],
  "image_url": [
    "https://ldb-phinf.pstatic.net/20251123_165/1763886169005g7xQx_JPEG/1000022563.jpg",
    "https://ldb-phinf.pstatic.net/20251123_230/1763886184431NRjdV_JPEG/1000022553.jpg",
    "https://ldb-phinf.pstatic.net/20251123_297/1763886184427zm9KT_JPEG/1000022559.jpg",
    "https://ldb-phinf.pstatic.net/20251123_219/1763886184443O4iMR_JPEG/1000022560.jpg",
    "https://ldb-phinf.pstatic.net/20251123_63/1763886169009gSA4x_JPEG/1000022561.jpg",
    "https://ldb-phinf.pstatic.net/20251123_225/1763886169010KkS4q_JPEG/1000022562.jpg",
    "https://ldb-phinf.pstatic.net/20250920_242/1758339762553pvKOB_JPEG/1000020570.jpg",
    "https://ldb-phinf.pstatic.net/20250816_56/1755326943398kBcpr_JPEG/1000020808.jpg",
    "https://ldb-phinf.pstatic.net/20250816_214/1755326937573bxnHJ_JPEG/1000020809.jpg",
    "https://ldb-phinf.pstatic.net/20250401_77/17435014585887m7VF_JPEG/KakaoTalk_20250401_151200305_01.jpg",
    "https://ldb-phinf.pstatic.net/20250401_280/1743501458533sATja_JPEG/KakaoTalk_20250401_151200305.jpg",
    "https://ldb-phinf.pstatic.net/20250302_226/17408838886661tirI_JPEG/1000018275.jpg",
    "https://ldb-phinf.pstatic.net/20250610_85/1749523410389R0UWn_JPEG/4.%BD%BA%C0%A7%C6%AE_%BF%E4%B0%C5%C6%AE_%BA%F9%BC%F6.jpg",
    "https://ldb-phinf.pstatic.net/20250610_209/1749523410343ptffL_JPEG/1.%B9%D0%C5%A9%C6%BC%B3%D3_%BA%F9%BC%F6.jpg",
    "https://ldb-phinf.pstatic.net/20250610_294/17495234103674LmKW_JPEG/2.%B8%C1%B0%ED_%BA%F9%BC%F6.jpg",
    "https://ldb-phinf.pstatic.net/20250610_148/1749523410478O4KME_JPEG/3.%B8%E1%B7%D0_%BA%F9%BC%F6.jpg",
    "https://ldb-phinf.pstatic.net/20250610_159/17495234103477SwJM_JPEG/6.%B9%D0%C5%A9%C6%BC%B3%D3%BA%F9%BC%F6%2B%C6%F7%B7%B9%BD%BA%C6%AE%B7%CE%B1%D7.jpg",
    "https://ldb-phinf.pstatic.net/20250302_26/1740883878434K2r9n_JPEG/1000018279.jpg",
    "https://ldb-phinf.pstatic.net/20250302_114/1740883871048440RJ_JPEG/1000018278.jpg",
    "https://ldb-phinf.pstatic.net/20250302_13/1740883839327a2EDU_JPEG/1000018284.jpg",
    "https://ldb-phinf.pstatic.net/20250201_165/1738404753857ShYIo_JPEG/1000017907.jpg",
    "https://ldb-phinf.pstatic.net/20250115_204/1736919256407XClKY_JPEG/2.jpg",
    "https://ldb-phinf.pstatic.net/20250115_88/1736919477706eeJQI_JPEG/%C7%C82.jpg"
  ]
}